[
    {
        "_id": "1b942c718896",
        "type": "06a8ed7cd071",
        "name": "Income",
        "description": "Income",
        "user": null,
        "parentId": null
    },
    {
        "_id": "bce6305b7385",
        "type": "988ddbb27007",
        "name": "Expenses",
        "description": "Expenses",
        "user": null,
        "parentId": null
    },
    {
        "_id": "7108d540ec8b",
        "type": "3a87574ddf9b",
        "name": "Assets",
        "description": "Assets",
        "user": null,
        "parentId": null
    },
    {
        "_id": "ad4b565c77f6",
        "name": "Equity",
        "type": "ee335689a943",
        "description": "Equity",
        "user": null,
        "parentId": null
    },
    {
        "_id": "cf685f10391e",
        "name": "Opening balance",
        "type": "ee335689a943",
        "description": "Opening balance",
        "user": null,
        "parentId": "ad4b565c77f6"
    }
]
